learn/seg_dec/seg_dec.v
module seg_dec (num,
                a_g);

    input[3:0] num;
    output[6:0] a_g;

    reg[6:0] a_g; // a_g(a,b,c,d,e,f,g)

    always @(num) begin
        case(num)
            4'd0: a_g   <= 7'b111_1110;
            4'd1: a_g   <= 7'b011_0000;
            4'd2: a_g   <= 7'b110_1101;
            4'd3: a_g   <= 7'b111_1001;
            4'd4: a_g   <= 7'b011_0010;
            4'd5: a_g   <= 7'b101_1011;
            4'd6: a_g   <= 7'b101_1111;
            4'd7: a_g   <= 7'b111_0000;
            4'd8: a_g   <= 7'b111_1111;
            4'd9: a_g   <= 7'b111_1011;
            default a_g <= 7'b000_0001;

        endcase
    end
endmodule

learn/seg_dec/seg_dec_tb.v
`timescale 10ns/100ps

module seg_dec_tb; wire[6:0] a_g; reg[3:0] num; seg_dec seg_dec_tb(.num(num), .a_g(a_g));

initial begin
    $dumpfile("learn/seg_dec/seg_dec.vcd");
    $dumpvars(0, seg_dec_tb);
end
initial begin
    num <= 4'b000;
    #200 $stop;
end
always #10 num <= num+1;

endmodule //seg_dec_tb

learn/seg_dec/seg_dec.vcd
$date
	Fri Nov 11 20:23:42 2022
$end
$version
	Icarus Verilog
$end
$timescale
	100ps
$end
$scope module seg_dec_tb $end
$scope module seg_dec_tb $end
$var wire 4 ! num [3:0] $end
$var reg 7 " a_g [6:0] $end
$upscope $end
$upscope $end
$enddefinitions $end
#0
$dumpvars
b1111110 "
b0 !
$end
#1000
b110000 "
b1 !
#2000
b1101101 "
b10 !
#3000
b1111001 "
b11 !
#4000
b110010 "
b100 !
#5000
b1011011 "
b101 !
#6000
b1011111 "
b110 !
#7000
b1110000 "
b111 !
#8000
b1111111 "
b1000 !
#9000
b1111011 "
b1001 !
#10000
b1 "
b1010 !
#11000
b1011 !
#12000
b1100 !
#13000
b1101 !
#14000
b1110 !
#15000
b1111 !
#16000
b1111110 "
b0 !
#17000
b110000 "
b1 !
#18000
b1101101 "
b10 !
#19000
b1111001 "
b11 !
