learn/sigma_16p/sigma_16p.v
module sigma_16p (clk,
                  res,
                  data_in,
                  syn_in,
                  data_out,
                  syn_out);

    input clk;
    input res;
    input[7:0] data_in;  // 采样信号
    input syn_in;        // 采样时钟

    output[11:0] data_out;  // 累加结果输出
    output syn_out;         // 累加和同步脉冲

    reg syn_in_n1; // syn_in的反向延时
    wire syn_pulse; // 采样信号时钟上升沿识别脉冲
    assign syn_pulse = syn_in&syn_in_n1;
    reg[3:0] con_syn;
    wire[7:0] comp_8; // 补码
    wire[11:0] d_12;  // 升位结果
    assign comp_8 = data_in[7]?{data_in[7], ~data_in[6:0]+1'b1}:data_in;  // 补码运算
    assign d_12   = {comp_8[7],comp_8[7],comp_8[7],comp_8[7],comp_8};
    reg[11:0] sigma;  // 累加计算
    reg[11:0] data_out;
    reg syn_out;

    always @(posedge clk or negedge res) begin
        if (~res)begin
            syn_in_n1 <= 0;con_syn <= 0;sigma <= 0;syn_out <= 0;data_out <= 0;
        end
        else begin
            syn_in_n1 <= ~syn_in;  // 自身会有延时
            if (syn_pulse)begin
                con_syn <= con_syn +1;
            end
                if (syn_pulse)begin
                    if (con_syn == 15)begin
                        sigma    <= d_12;
                        data_out <= sigma;
                        syn_out  <= 1;
                    end
                    else begin
                        sigma <= sigma+d_12;
                    end
                end
                else begin

                    syn_out <= 0;
                end
        end
    end

endmodule //sigma_16p

learn/sigma_16p/sigma_16p_tb.v
`timescale 1ns/100ps
module sigma_16p_tb; reg clk, res; reg[7:0] data_in; reg syn_in; wire[11:0] data_out; wire syn_out; sigma_16p sigma_16p_tb(.clk(clk), .res(res), .data_in(data_in), .syn_in(syn_in), .data_out(data_out), .syn_out(syn_out));



initial begin
    $dumpfile("learn/sigma_16p/sigma_16p.vcd");
    $dumpvars(0,sigma_16p_tb);
end

initial begin
    // clk  <= 0;res  <= 0; data_in  <= 1;syn_in  <= 0;
    clk     <= 0;res     <= 0; data_in     <= 8'b1;syn_in     <= 0;
    #17 res <= 1;
    #100000 $stop;
end

always #5 clk      = ~clk;
always #100 syn_in = ~syn_in;
endmodule //sigma_16p

learn/sigma_16p/sigma_16p.vcd
$date
	Fri Nov 11 23:05:14 2022
$end
$version
	Icarus Verilog
$end
$timescale
	100ps
$end
$scope module sigma_16p_tb $end
$scope module sigma_16p_tb $end
$var wire 1 ! clk $end
$var wire 8 " data_in [7:0] $end
$var wire 1 # res $end
$var wire 1 $ syn_in $end
$var wire 1 % syn_pulse $end
$var wire 12 & d_12 [11:0] $end
$var wire 8 ' comp_8 [7:0] $end
$var reg 4 ( con_syn [3:0] $end
$var reg 12 ) data_out [11:0] $end
$var reg 12 * sigma [11:0] $end
$var reg 1 + syn_in_n1 $end
$var reg 1 , syn_out $end
$upscope $end
$upscope $end
$enddefinitions $end
#0
$dumpvars
0,
0+
b0 *
b0 )
b0 (
b1 '
b1 &
0%
0$
0#
b1 "
0!
$end
#50
1!
#100
0!
#150
1!
#170
1#
#200
0!
#250
1+
1!
#300
0!
#350
1!
#400
0!
#450
1!
#500
0!
#550
1!
#600
0!
#650
1!
#700
0!
#750
1!
#800
0!
#850
1!
#900
0!
#950
1!
#1000
1%
0!
1$
#1050
0%
b1 *
b1 (
0+
1!
#1100
0!
#1150
1!
#1200
0!
#1250
1!
#1300
0!
#1350
1!
#1400
0!
#1450
1!
#1500
0!
#1550
1!
#1600
0!
#1650
1!
#1700
0!
#1750
1!
#1800
0!
#1850
1!
#1900
0!
#1950
1!
#2000
0!
0$
#2050
1+
1!
#2100
0!
#2150
1!
#2200
0!
#2250
1!
#2300
0!
#2350
1!
#2400
0!
#2450
1!
#2500
0!
#2550
1!
#2600
0!
#2650
1!
#2700
0!
#2750
1!
#2800
0!
#2850
1!
#2900
0!
#2950
1!
#3000
1%
0!
1$
#3050
0%
b10 *
b10 (
0+
1!
#3100
0!
#3150
1!
#3200
0!
#3250
1!
#3300
0!
#3350
1!
#3400
0!
#3450
1!
#3500
0!
#3550
1!
#3600
0!
#3650
1!
#3700
0!
#3750
1!
#3800
0!
#3850
1!
#3900
0!
#3950
1!
#4000
0!
0$
#4050
1+
1!
#4100
0!
#4150
1!
#4200
0!
#4250
1!
#4300
0!
#4350
1!
#4400
0!
#4450
1!
#4500
0!
#4550
1!
#4600
0!
#4650
1!
#4700
0!
#4750
1!
#4800
0!
#4850
1!
#4900
0!
#4950
1!
#5000
1%
0!
1$
#5050
0%
b11 *
b11 (
0+
1!
#5100
0!
#5150
1!
#5200
0!
#5250
1!
#5300
0!
#5350
1!
#5400
0!
#5450
1!
#5500
0!
#5550
1!
#5600
0!
#5650
1!
#5700
0!
#5750
1!
#5800
0!
#5850
1!
#5900
0!
#5950
1!
#6000
0!
0$
#6050
1+
1!
#6100
0!
#6150
1!
#6200
0!
#6250
1!
#6300
0!
#6350
1!
#6400
0!
#6450
1!
#6500
0!
#6550
1!
#6600
0!
#6650
1!
#6700
0!
#6750
1!
#6800
0!
#6850
1!
#6900
0!
#6950
1!
#7000
1%
0!
1$
#7050
0%
b100 *
b100 (
0+
1!
#7100
0!
#7150
1!
#7200
0!
#7250
1!
#7300
0!
#7350
1!
#7400
0!
#7450
1!
#7500
0!
#7550
1!
#7600
0!
#7650
1!
#7700
0!
#7750
1!
#7800
0!
#7850
1!
#7900
0!
#7950
1!
#8000
0!
0$
#8050
1+
1!
#8100
0!
#8150
1!
#8200
0!
#8250
1!
#8300
0!
#8350
1!
#8400
0!
#8450
1!
#8500
0!
#8550
1!
#8600
0!
#8650
1!
#8700
0!
#8750
1!
#8800
0!
#8850
1!
#8900
0!
#8950
1!
#9000
1%
0!
1$
#9050
0%
b101 *
b101 (
0+
1!
#9100
0!
#9150
1!
#9200
0!
#9250
1!
#9300
0!
#9350
1!
#9400
0!
#9450
1!
#9500
0!
#9550
1!
#9600
0!
#9650
1!
#9700
0!
#9750
1!
#9800
0!
#9850
1!
#9900
0!
#9950
1!
#10000
0!
0$
#10050
1+
1!
#10100
0!
#10150
1!
#10200
0!
#10250
1!
#10300
0!
#10350
1!
#10400
0!
#10450
1!
#10500
0!
#10550
1!
#10600
0!
#10650
1!
#10700
0!
#10750
1!
#10800
0!
#10850
1!
#10900
0!
#10950
1!
#11000
1%
0!
1$
#11050
0%
b110 *
b110 (
0+
1!
#11100
0!
#11150
1!
#11200
0!
#11250
1!
#11300
0!
#11350
1!
#11400
0!
#11450
1!
#11500
0!
#11550
1!
#11600
0!
#11650
1!
#11700
0!
#11750
1!
#11800
0!
#11850
1!
#11900
0!
#11950
1!
#12000
0!
0$
#12050
1+
1!
#12100
0!
#12150
1!
#12200
0!
#12250
1!
#12300
0!
#12350
1!
#12400
0!
#12450
1!
#12500
0!
#12550
1!
#12600
0!
#12650
1!
#12700
0!
#12750
1!
#12800
0!
#12850
1!
#12900
0!
#12950
1!
#13000
1%
0!
1$
#13050
0%
b111 *
b111 (
0+
1!
#13100
0!
#13150
1!
#13200
0!
#13250
1!
#13300
0!
#13350
1!
#13400
0!
#13450
1!
#13500
0!
#13550
1!
#13600
0!
#13650
1!
#13700
0!
#13750
1!
#13800
0!
#13850
1!
#13900
0!
#13950
1!
#14000
0!
0$
#14050
1+
1!
#14100
0!
#14150
1!
#14200
0!
#14250
1!
#14300
0!
#14350
1!
#14400
0!
#14450
1!
#14500
0!
#14550
1!
#14600
0!
#14650
1!
#14700
0!
#14750
1!
#14800
0!
#14850
1!
#14900
0!
#14950
1!
#15000
1%
0!
1$
#15050
0%
b1000 *
b1000 (
0+
1!
#15100
0!
#15150
1!
#15200
0!
#15250
1!
#15300
0!
#15350
1!
#15400
0!
#15450
1!
#15500
0!
#15550
1!
#15600
0!
#15650
1!
#15700
0!
#15750
1!
#15800
0!
#15850
1!
#15900
0!
#15950
1!
#16000
0!
0$
#16050
1+
1!
#16100
0!
#16150
1!
#16200
0!
#16250
1!
#16300
0!
#16350
1!
#16400
0!
#16450
1!
#16500
0!
#16550
1!
#16600
0!
#16650
1!
#16700
0!
#16750
1!
#16800
0!
#16850
1!
#16900
0!
#16950
1!
#17000
1%
0!
1$
#17050
0%
b1001 *
b1001 (
0+
1!
#17100
0!
#17150
1!
#17200
0!
#17250
1!
#17300
0!
#17350
1!
#17400
0!
#17450
1!
#17500
0!
#17550
1!
#17600
0!
#17650
1!
#17700
0!
#17750
1!
#17800
0!
#17850
1!
#17900
0!
#17950
1!
#18000
0!
0$
#18050
1+
1!
#18100
0!
#18150
1!
#18200
0!
#18250
1!
#18300
0!
#18350
1!
#18400
0!
#18450
1!
#18500
0!
#18550
1!
#18600
0!
#18650
1!
#18700
0!
#18750
1!
#18800
0!
#18850
1!
#18900
0!
#18950
1!
#19000
1%
0!
1$
#19050
0%
b1010 *
b1010 (
0+
1!
#19100
0!
#19150
1!
#19200
0!
#19250
1!
#19300
0!
#19350
1!
#19400
0!
#19450
1!
#19500
0!
#19550
1!
#19600
0!
#19650
1!
#19700
0!
#19750
1!
#19800
0!
#19850
1!
#19900
0!
#19950
1!
#20000
0!
0$
#20050
1+
1!
#20100
0!
#20150
1!
#20200
0!
#20250
1!
#20300
0!
#20350
1!
#20400
0!
#20450
1!
#20500
0!
#20550
1!
#20600
0!
#20650
1!
#20700
0!
#20750
1!
#20800
0!
#20850
1!
#20900
0!
#20950
1!
#21000
1%
0!
1$
#21050
0%
b1011 *
b1011 (
0+
1!
#21100
0!
#21150
1!
#21200
0!
#21250
1!
#21300
0!
#21350
1!
#21400
0!
#21450
1!
#21500
0!
#21550
1!
#21600
0!
#21650
1!
#21700
0!
#21750
1!
#21800
0!
#21850
1!
#21900
0!
#21950
1!
#22000
0!
0$
#22050
1+
1!
#22100
0!
#22150
1!
#22200
0!
#22250
1!
#22300
0!
#22350
1!
#22400
0!
#22450
1!
#22500
0!
#22550
1!
#22600
0!
#22650
1!
#22700
0!
#22750
1!
#22800
0!
#22850
1!
#22900
0!
#22950
1!
#23000
1%
0!
1$
#23050
0%
b1100 *
b1100 (
0+
1!
#23100
0!
#23150
1!
#23200
0!
#23250
1!
#23300
0!
#23350
1!
#23400
0!
#23450
1!
#23500
0!
#23550
1!
#23600
0!
#23650
1!
#23700
0!
#23750
1!
#23800
0!
#23850
1!
#23900
0!
#23950
1!
#24000
0!
0$
#24050
1+
1!
#24100
0!
#24150
1!
#24200
0!
#24250
1!
#24300
0!
#24350
1!
#24400
0!
#24450
1!
#24500
0!
#24550
1!
#24600
0!
#24650
1!
#24700
0!
#24750
1!
#24800
0!
#24850
1!
#24900
0!
#24950
1!
#25000
1%
0!
1$
#25050
0%
b1101 *
b1101 (
0+
1!
#25100
0!
#25150
1!
#25200
0!
#25250
1!
#25300
0!
#25350
1!
#25400
0!
#25450
1!
#25500
0!
#25550
1!
#25600
0!
#25650
1!
#25700
0!
#25750
1!
#25800
0!
#25850
1!
#25900
0!
#25950
1!
#26000
0!
0$
#26050
1+
1!
#26100
0!
#26150
1!
#26200
0!
#26250
1!
#26300
0!
#26350
1!
#26400
0!
#26450
1!
#26500
0!
#26550
1!
#26600
0!
#26650
1!
#26700
0!
#26750
1!
#26800
0!
#26850
1!
#26900
0!
#26950
1!
#27000
1%
0!
1$
#27050
0%
b1110 *
b1110 (
0+
1!
#27100
0!
#27150
1!
#27200
0!
#27250
1!
#27300
0!
#27350
1!
#27400
0!
#27450
1!
#27500
0!
#27550
1!
#27600
0!
#27650
1!
#27700
0!
#27750
1!
#27800
0!
#27850
1!
#27900
0!
#27950
1!
#28000
0!
0$
#28050
1+
1!
#28100
0!
#28150
1!
#28200
0!
#28250
1!
#28300
0!
#28350
1!
#28400
0!
#28450
1!
#28500
0!
#28550
1!
#28600
0!
#28650
1!
#28700
0!
#28750
1!
#28800
0!
#28850
1!
#28900
0!
#28950
1!
#29000
1%
0!
1$
#29050
0%
b1111 *
b1111 (
0+
1!
#29100
0!
#29150
1!
#29200
0!
#29250
1!
#29300
0!
#29350
1!
#29400
0!
#29450
1!
#29500
0!
#29550
1!
#29600
0!
#29650
1!
#29700
0!
#29750
1!
#29800
0!
#29850
1!
#29900
0!
#29950
1!
#30000
0!
0$
#30050
1+
1!
#30100
0!
#30150
1!
#30200
0!
#30250
1!
#30300
0!
#30350
1!
#30400
0!
#30450
1!
#30500
0!
#30550
1!
#30600
0!
#30650
1!
#30700
0!
#30750
1!
#30800
0!
#30850
1!
#30900
0!
#30950
1!
#31000
1%
0!
1$
#31050
0%
1,
b1111 )
b1 *
b0 (
0+
1!
#31100
0!
#31150
0,
1!
#31200
0!
#31250
1!
#31300
0!
#31350
1!
#31400
0!
#31450
1!
#31500
0!
#31550
1!
#31600
0!
#31650
1!
#31700
0!
#31750
1!
#31800
0!
#31850
1!
#31900
0!
#31950
1!
#32000
0!
0$
#32050
1+
1!
#32100
0!
#32150
1!
#32200
0!
#32250
1!
#32300
0!
#32350
1!
#32400
0!
#32450
1!
#32500
0!
#32550
1!
#32600
0!
#32650
1!
#32700
0!
#32750
1!
#32800
0!
#32850
1!
#32900
0!
#32950
1!
#33000
1%
0!
1$
#33050
0%
b10 *
b1 (
0+
1!
#33100
0!
#33150
1!
#33200
0!
#33250
1!
#33300
0!
#33350
1!
#33400
0!
#33450
1!
#33500
0!
#33550
1!
#33600
0!
#33650
1!
#33700
0!
#33750
1!
#33800
0!
#33850
1!
#33900
0!
#33950
1!
#34000
0!
0$
#34050
1+
1!
#34100
0!
#34150
1!
#34200
0!
#34250
1!
#34300
0!
#34350
1!
#34400
0!
#34450
1!
#34500
0!
#34550
1!
#34600
0!
#34650
1!
#34700
0!
#34750
1!
#34800
0!
#34850
1!
#34900
0!
#34950
1!
#35000
1%
0!
1$
#35050
0%
b11 *
b10 (
0+
1!
#35100
0!
#35150
1!
#35200
0!
#35250
1!
#35300
0!
#35350
1!
#35400
0!
#35450
1!
#35500
0!
#35550
1!
#35600
0!
#35650
1!
#35700
0!
#35750
1!
#35800
0!
#35850
1!
#35900
0!
#35950
1!
#36000
0!
0$
#36050
1+
1!
#36100
0!
#36150
1!
#36200
0!
#36250
1!
#36300
0!
#36350
1!
#36400
0!
#36450
1!
#36500
0!
#36550
1!
#36600
0!
#36650
1!
#36700
0!
#36750
1!
#36800
0!
#36850
1!
#36900
0!
#36950
1!
#37000
1%
0!
1$
#37050
0%
b100 *
b11 (
0+
1!
#37100
0!
#37150
1!
#37200
0!
#37250
1!
#37300
0!
#37350
1!
#37400
0!
#37450
1!
#37500
0!
#37550
1!
#37600
0!
#37650
1!
#37700
0!
#37750
1!
#37800
0!
#37850
1!
#37900
0!
#37950
1!
#38000
0!
0$
#38050
1+
1!
#38100
0!
#38150
1!
#38200
0!
#38250
1!
#38300
0!
#38350
1!
#38400
0!
#38450
1!
#38500
0!
#38550
1!
#38600
0!
#38650
1!
#38700
0!
#38750
1!
#38800
0!
#38850
1!
#38900
0!
#38950
1!
#39000
1%
0!
1$
#39050
0%
b101 *
b100 (
0+
1!
#39100
0!
#39150
1!
#39200
0!
#39250
1!
#39300
0!
#39350
1!
#39400
0!
#39450
1!
#39500
0!
#39550
1!
#39600
0!
#39650
1!
#39700
0!
#39750
1!
#39800
0!
#39850
1!
#39900
0!
#39950
1!
#40000
0!
0$
#40050
1+
1!
#40100
0!
#40150
1!
#40200
0!
#40250
1!
#40300
0!
#40350
1!
#40400
0!
#40450
1!
#40500
0!
#40550
1!
#40600
0!
#40650
1!
#40700
0!
#40750
1!
#40800
0!
#40850
1!
#40900
0!
#40950
1!
#41000
1%
0!
1$
#41050
0%
b110 *
b101 (
0+
1!
#41100
0!
#41150
1!
#41200
0!
#41250
1!
#41300
0!
#41350
1!
#41400
0!
#41450
1!
#41500
0!
#41550
1!
#41600
0!
#41650
1!
#41700
0!
#41750
1!
#41800
0!
#41850
1!
#41900
0!
#41950
1!
#42000
0!
0$
#42050
1+
1!
#42100
0!
#42150
1!
#42200
0!
#42250
1!
#42300
0!
#42350
1!
#42400
0!
#42450
1!
#42500
0!
#42550
1!
#42600
0!
#42650
1!
#42700
0!
#42750
1!
#42800
0!
#42850
1!
#42900
0!
#42950
1!
#43000
1%
0!
1$
#43050
0%
b111 *
b110 (
0+
1!
#43100
0!
#43150
1!
#43200
0!
#43250
1!
#43300
0!
#43350
1!
#43400
0!
#43450
1!
#43500
0!
#43550
1!
#43600
0!
#43650
1!
#43700
0!
#43750
1!
#43800
0!
#43850
1!
#43900
0!
#43950
1!
#44000
0!
0$
#44050
1+
1!
#44100
0!
#44150
1!
#44200
0!
#44250
1!
#44300
0!
#44350
1!
#44400
0!
#44450
1!
#44500
0!
#44550
1!
#44600
0!
#44650
1!
#44700
0!
#44750
1!
#44800
0!
#44850
1!
#44900
0!
#44950
1!
#45000
1%
0!
1$
#45050
0%
b1000 *
b111 (
0+
1!
#45100
0!
#45150
1!
#45200
0!
#45250
1!
#45300
0!
#45350
1!
#45400
0!
#45450
1!
#45500
0!
#45550
1!
#45600
0!
#45650
1!
#45700
0!
#45750
1!
#45800
0!
#45850
1!
#45900
0!
#45950
1!
#46000
0!
0$
#46050
1+
1!
#46100
0!
#46150
1!
#46200
0!
#46250
1!
#46300
0!
#46350
1!
#46400
0!
#46450
1!
#46500
0!
#46550
1!
#46600
0!
#46650
1!
#46700
0!
#46750
1!
#46800
0!
#46850
1!
#46900
0!
#46950
1!
#47000
1%
0!
1$
#47050
0%
b1001 *
b1000 (
0+
1!
#47100
0!
#47150
1!
#47200
0!
#47250
1!
#47300
0!
#47350
1!
#47400
0!
#47450
1!
#47500
0!
#47550
1!
#47600
0!
#47650
1!
#47700
0!
#47750
1!
#47800
0!
#47850
1!
#47900
0!
#47950
1!
#48000
0!
0$
#48050
1+
1!
#48100
0!
#48150
1!
#48200
0!
#48250
1!
#48300
0!
#48350
1!
#48400
0!
#48450
1!
#48500
0!
#48550
1!
#48600
0!
#48650
1!
#48700
0!
#48750
1!
#48800
0!
#48850
1!
#48900
0!
#48950
1!
#49000
1%
0!
1$
#49050
0%
b1010 *
b1001 (
0+
1!
#49100
0!
#49150
1!
#49200
0!
#49250
1!
#49300
0!
#49350
1!
#49400
0!
#49450
1!
#49500
0!
#49550
1!
#49600
0!
#49650
1!
#49700
0!
#49750
1!
#49800
0!
#49850
1!
#49900
0!
#49950
1!
#50000
0!
0$
#50050
1+
1!
#50100
0!
#50150
1!
#50200
0!
#50250
1!
#50300
0!
#50350
1!
#50400
0!
#50450
1!
#50500
0!
#50550
1!
#50600
0!
#50650
1!
#50700
0!
#50750
1!
#50800
0!
#50850
1!
#50900
0!
#50950
1!
#51000
1%
0!
1$
#51050
0%
b1011 *
b1010 (
0+
1!
#51100
0!
#51150
1!
#51200
0!
#51250
1!
#51300
0!
#51350
1!
#51400
0!
#51450
1!
#51500
0!
#51550
1!
#51600
0!
#51650
1!
#51700
0!
#51750
1!
#51800
0!
#51850
1!
#51900
0!
#51950
1!
#52000
0!
0$
#52050
1+
1!
#52100
0!
#52150
1!
#52200
0!
#52250
1!
#52300
0!
#52350
1!
#52400
0!
#52450
1!
#52500
0!
#52550
1!
#52600
0!
#52650
1!
#52700
0!
#52750
1!
#52800
0!
#52850
1!
#52900
0!
#52950
1!
#53000
1%
0!
1$
#53050
0%
b1100 *
b1011 (
0+
1!
#53100
0!
#53150
1!
#53200
0!
#53250
1!
#53300
0!
#53350
1!
#53400
0!
#53450
1!
#53500
0!
#53550
1!
#53600
0!
#53650
1!
#53700
0!
#53750
1!
#53800
0!
#53850
1!
#53900
0!
#53950
1!
#54000
0!
0$
#54050
1+
1!
#54100
0!
#54150
1!
#54200
0!
#54250
1!
#54300
0!
#54350
1!
#54400
0!
#54450
1!
#54500
0!
#54550
1!
#54600
0!
#54650
1!
#54700
0!
#54750
1!
#54800
0!
#54850
1!
#54900
0!
#54950
1!
#55000
1%
0!
1$
#55050
0%
b1101 *
b1100 (
0+
1!
#55100
0!
#55150
1!
#55200
0!
#55250
1!
#55300
0!
#55350
1!
#55400
0!
#55450
1!
#55500
0!
#55550
1!
#55600
0!
#55650
1!
#55700
0!
#55750
1!
#55800
0!
#55850
1!
#55900
0!
#55950
1!
#56000
0!
0$
#56050
1+
1!
#56100
0!
#56150
1!
#56200
0!
#56250
1!
#56300
0!
#56350
1!
#56400
0!
#56450
1!
#56500
0!
#56550
1!
#56600
0!
#56650
1!
#56700
0!
#56750
1!
#56800
0!
#56850
1!
#56900
0!
#56950
1!
#57000
1%
0!
1$
#57050
0%
b1110 *
b1101 (
0+
1!
#57100
0!
#57150
1!
#57200
0!
#57250
1!
#57300
0!
#57350
1!
#57400
0!
#57450
1!
#57500
0!
#57550
1!
#57600
0!
#57650
1!
#57700
0!
#57750
1!
#57800
0!
#57850
1!
#57900
0!
#57950
1!
#58000
0!
0$
#58050
1+
1!
#58100
0!
#58150
1!
#58200
0!
#58250
1!
#58300
0!
#58350
1!
#58400
0!
#58450
1!
#58500
0!
#58550
1!
#58600
0!
#58650
1!
#58700
0!
#58750
1!
#58800
0!
#58850
1!
#58900
0!
#58950
1!
#59000
1%
0!
1$
#59050
0%
b1111 *
b1110 (
0+
1!
#59100
0!
#59150
1!
#59200
0!
#59250
1!
#59300
0!
#59350
1!
#59400
0!
#59450
1!
#59500
0!
#59550
1!
#59600
0!
#59650
1!
#59700
0!
#59750
1!
#59800
0!
#59850
1!
#59900
0!
#59950
1!
#60000
0!
0$
#60050
1+
1!
#60100
0!
#60150
1!
#60200
0!
#60250
1!
#60300
0!
#60350
1!
#60400
0!
#60450
1!
#60500
0!
#60550
1!
#60600
0!
#60650
1!
#60700
0!
#60750
1!
#60800
0!
#60850
1!
#60900
0!
#60950
1!
#61000
1%
0!
1$
#61050
0%
b10000 *
b1111 (
0+
1!
#61100
0!
#61150
1!
#61200
0!
#61250
1!
#61300
0!
#61350
1!
#61400
0!
#61450
1!
#61500
0!
#61550
1!
#61600
0!
#61650
1!
#61700
0!
#61750
1!
#61800
0!
#61850
1!
#61900
0!
#61950
1!
#62000
0!
0$
#62050
1+
1!
#62100
0!
#62150
1!
#62200
0!
#62250
1!
#62300
0!
#62350
1!
#62400
0!
#62450
1!
#62500
0!
#62550
1!
#62600
0!
#62650
1!
#62700
0!
#62750
1!
#62800
0!
#62850
1!
#62900
0!
#62950
1!
#63000
1%
0!
1$
#63050
0%
1,
b10000 )
b1 *
b0 (
0+
1!
#63100
0!
#63150
0,
1!
#63200
0!
#63250
1!
#63300
0!
#63350
1!
#63400
0!
#63450
1!
#63500
0!
#63550
1!
#63600
0!
#63650
1!
#63700
0!
#63750
1!
#63800
0!
#63850
1!
#63900
0!
#63950
1!
#64000
0!
0$
#64050
1+
1!
#64100
0!
#64150
1!
#64200
0!
#64250
1!
#64300
0!
#64350
1!
#64400
0!
#64450
1!
#64500
0!
#64550
1!
#64600
0!
#64650
1!
#64700
0!
#64750
1!
#64800
0!
#64850
1!
#64900
0!
#64950
1!
#65000
1%
0!
1$
#65050
0%
b10 *
b1 (
0+
1!
#65100
0!
#65150
1!
#65200
0!
#65250
1!
#65300
0!
#65350
1!
#65400
0!
#65450
1!
#65500
0!
#65550
1!
#65600
0!
#65650
1!
#65700
0!
#65750
1!
#65800
0!
#65850
1!
#65900
0!
#65950
1!
#66000
0!
0$
#66050
1+
1!
#66100
0!
#66150
1!
#66200
0!
#66250
1!
#66300
0!
#66350
1!
#66400
0!
#66450
1!
#66500
0!
#66550
1!
#66600
0!
#66650
1!
#66700
0!
#66750
1!
#66800
0!
#66850
1!
#66900
0!
#66950
1!
#67000
1%
0!
1$
#67050
0%
b11 *
b10 (
0+
1!
#67100
0!
#67150
1!
#67200
0!
#67250
1!
#67300
0!
#67350
1!
#67400
0!
#67450
1!
#67500
0!
#67550
1!
#67600
0!
#67650
1!
#67700
0!
#67750
1!
#67800
0!
#67850
1!
#67900
0!
#67950
1!
#68000
0!
0$
#68050
1+
1!
#68100
0!
#68150
1!
#68200
0!
#68250
1!
#68300
0!
#68350
1!
#68400
0!
#68450
1!
#68500
0!
#68550
1!
#68600
0!
#68650
1!
#68700
0!
#68750
1!
#68800
0!
#68850
1!
#68900
0!
#68950
1!
#69000
1%
0!
1$
#69050
0%
b100 *
b11 (
0+
1!
#69100
0!
#69150
1!
#69200
0!
#69250
1!
#69300
0!
#69350
1!
#69400
0!
#69450
1!
#69500
0!
#69550
1!
#69600
0!
#69650
1!
#69700
0!
#69750
1!
#69800
0!
#69850
1!
#69900
0!
#69950
1!
#70000
0!
0$
#70050
1+
1!
#70100
0!
#70150
1!
#70200
0!
#70250
1!
#70300
0!
#70350
1!
#70400
0!
#70450
1!
#70500
0!
#70550
1!
#70600
0!
#70650
1!
#70700
0!
#70750
1!
#70800
0!
#70850
1!
#70900
0!
#70950
1!
#71000
1%
0!
1$
#71050
0%
b101 *
b100 (
0+
1!
#71100
0!
#71150
1!
#71200
0!
#71250
1!
#71300
0!
#71350
1!
#71400
0!
#71450
1!
#71500
0!
#71550
1!
#71600
0!
#71650
1!
#71700
0!
#71750
1!
#71800
0!
#71850
1!
#71900
0!
#71950
1!
#72000
0!
0$
#72050
1+
1!
#72100
0!
#72150
1!
#72200
0!
#72250
1!
#72300
0!
#72350
1!
#72400
0!
#72450
1!
#72500
0!
#72550
1!
#72600
0!
#72650
1!
#72700
0!
#72750
1!
#72800
0!
#72850
1!
#72900
0!
#72950
1!
#73000
1%
0!
1$
#73050
0%
b110 *
b101 (
0+
1!
#73100
0!
#73150
1!
#73200
0!
#73250
1!
#73300
0!
#73350
1!
#73400
0!
#73450
1!
#73500
0!
#73550
1!
#73600
0!
#73650
1!
#73700
0!
#73750
1!
#73800
0!
#73850
1!
#73900
0!
#73950
1!
#74000
0!
0$
#74050
1+
1!
#74100
0!
#74150
1!
#74200
0!
#74250
1!
#74300
0!
#74350
1!
#74400
0!
#74450
1!
#74500
0!
#74550
1!
#74600
0!
#74650
1!
#74700
0!
#74750
1!
#74800
0!
#74850
1!
#74900
0!
#74950
1!
#75000
1%
0!
1$
#75050
0%
b111 *
b110 (
0+
1!
#75100
0!
#75150
1!
#75200
0!
#75250
1!
#75300
0!
#75350
1!
#75400
0!
#75450
1!
#75500
0!
#75550
1!
#75600
0!
#75650
1!
#75700
0!
#75750
1!
#75800
0!
#75850
1!
#75900
0!
#75950
1!
#76000
0!
0$
#76050
1+
1!
#76100
0!
#76150
1!
#76200
0!
#76250
1!
#76300
0!
#76350
1!
#76400
0!
#76450
1!
#76500
0!
#76550
1!
#76600
0!
#76650
1!
#76700
0!
#76750
1!
#76800
0!
#76850
1!
#76900
0!
#76950
1!
#77000
1%
0!
1$
#77050
0%
b1000 *
b111 (
0+
1!
#77100
0!
#77150
1!
#77200
0!
#77250
1!
#77300
0!
#77350
1!
#77400
0!
#77450
1!
#77500
0!
#77550
1!
#77600
0!
#77650
1!
#77700
0!
#77750
1!
#77800
0!
#77850
1!
#77900
0!
#77950
1!
#78000
0!
0$
#78050
1+
1!
#78100
0!
#78150
1!
#78200
0!
#78250
1!
#78300
0!
#78350
1!
#78400
0!
#78450
1!
#78500
0!
#78550
1!
#78600
0!
#78650
1!
#78700
0!
#78750
1!
#78800
0!
#78850
1!
#78900
0!
#78950
1!
#79000
1%
0!
1$
#79050
0%
b1001 *
b1000 (
0+
1!
#79100
0!
#79150
1!
#79200
0!
#79250
1!
#79300
0!
#79350
1!
#79400
0!
#79450
1!
#79500
0!
#79550
1!
#79600
0!
#79650
1!
#79700
0!
#79750
1!
#79800
0!
#79850
1!
#79900
0!
#79950
1!
#80000
0!
0$
#80050
1+
1!
#80100
0!
#80150
1!
#80200
0!
#80250
1!
#80300
0!
#80350
1!
#80400
0!
#80450
1!
#80500
0!
#80550
1!
#80600
0!
#80650
1!
#80700
0!
#80750
1!
#80800
0!
#80850
1!
#80900
0!
#80950
1!
#81000
1%
0!
1$
#81050
0%
b1010 *
b1001 (
0+
1!
#81100
0!
#81150
1!
#81200
0!
#81250
1!
#81300
0!
#81350
1!
#81400
0!
#81450
1!
#81500
0!
#81550
1!
#81600
0!
#81650
1!
#81700
0!
#81750
1!
#81800
0!
#81850
1!
#81900
0!
#81950
1!
#82000
0!
0$
#82050
1+
1!
#82100
0!
#82150
1!
#82200
0!
#82250
1!
#82300
0!
#82350
1!
#82400
0!
#82450
1!
#82500
0!
#82550
1!
#82600
0!
#82650
1!
#82700
0!
#82750
1!
#82800
0!
#82850
1!
#82900
0!
#82950
1!
#83000
1%
0!
1$
#83050
0%
b1011 *
b1010 (
0+
1!
#83100
0!
#83150
1!
#83200
0!
#83250
1!
#83300
0!
#83350
1!
#83400
0!
#83450
1!
#83500
0!
#83550
1!
#83600
0!
#83650
1!
#83700
0!
#83750
1!
#83800
0!
#83850
1!
#83900
0!
#83950
1!
#84000
0!
0$
#84050
1+
1!
#84100
0!
#84150
1!
#84200
0!
#84250
1!
#84300
0!
#84350
1!
#84400
0!
#84450
1!
#84500
0!
#84550
1!
#84600
0!
#84650
1!
#84700
0!
#84750
1!
#84800
0!
#84850
1!
#84900
0!
#84950
1!
#85000
1%
0!
1$
#85050
0%
b1100 *
b1011 (
0+
1!
#85100
0!
#85150
1!
#85200
0!
#85250
1!
#85300
0!
#85350
1!
#85400
0!
#85450
1!
#85500
0!
#85550
1!
#85600
0!
#85650
1!
#85700
0!
#85750
1!
#85800
0!
#85850
1!
#85900
0!
#85950
1!
#86000
0!
0$
#86050
1+
1!
#86100
0!
#86150
1!
#86200
0!
#86250
1!
#86300
0!
#86350
1!
#86400
0!
#86450
1!
#86500
0!
#86550
1!
#86600
0!
#86650
1!
#86700
0!
#86750
1!
#86800
0!
#86850
1!
#86900
0!
#86950
1!
#87000
1%
0!
1$
#87050
0%
b1101 *
b1100 (
0+
1!
#87100
0!
#87150
1!
#87200
0!
#87250
1!
#87300
0!
#87350
1!
#87400
0!
#87450
1!
