learn/fn_sw_4/fn_sw_4.v
`timescale 1ns/10ps

module fn_sw_4(a,
               b,
               sel,
               y);
    input a;
    input b;
    input sel;
    output y;

    reg y;
    always @(a or b or sel) begin
        case(sel)
            2'b00:begin
                y <= a&b;
            end
            2'b01:begin
                y <= a|b;
            end
            2'b10:begin
                y <= a^b;
            end
            2'b11:begin
                y <= ~(a^b);
            end
        endcase
    end
    
endmodule

learn/fn_sw_4/fn_sw_4_tb.v
`timescale 1ns/10ps
module fn_sw_4_tb; reg[3:0] absel; wire y; fn_sw_4 fn_sw_4_tb(.a(absel[0]), .b(absel[1]), .sel(absel[2]), .y(y));

initial begin
    $dumpfile("learn/fn_sw_4/fn_sw_4.vcd");  // 指定VCD文件的名字为wave.vcd，仿真信息将记录到此文件
    $dumpvars(0, fn_sw_4_tb);  // 指定层次数为0，则tb_code 模块及其下面各层次的所有信号将被记录
    // #10000 $finish;
end

initial begin
    absel <= 0;
    #200 $stop;
end

always #10 absel <= absel+1;

endmodule

learn/fn_sw_4/fn_sw_4.vcd
$date
	Fri Nov 11 19:20:55 2022
$end
$version
	Icarus Verilog
$end
$timescale
	10ps
$end
$scope module fn_sw_4_tb $end
$scope module fn_sw_4_tb $end
$var wire 1 ! a $end
$var wire 1 " b $end
$var wire 1 # sel $end
$var reg 1 $ y $end
$upscope $end
$upscope $end
$enddefinitions $end
#0
$dumpvars
0$
0#
0"
0!
$end
#1000
1!
#2000
0!
1"
#3000
1$
1!
#4000
0$
0!
0"
1#
#5000
1$
1!
#6000
0!
1"
#7000
1!
#8000
0$
0!
0"
0#
#9000
1!
#10000
0!
1"
#11000
1$
1!
#12000
0$
0!
0"
1#
#13000
1$
1!
#14000
0!
1"
#15000
1!
#16000
0$
0!
0"
0#
#17000
1!
#18000
0!
1"
#19000
1$
1!
