learn/fn_sw/fn_sw.v
`timescale 1ns/10ps
// module fn_sw(a,
//              b,
//              sel,
//              y);
//     input a;
//     input b;
//     input sel;
//     output y;

//     assign y = sel?(a^b):(a&b);

// endmodule


// always实现方式
module fn_sw(a,
             b,
             sel,
             y);
    input a;
    input b;
    input sel;
    output y;

    reg y;
    always @(a or b or sel) begin
        if (sel == 1) begin
            y <= a^b;
        end
        else begin
            y <= a&b;
        end
    end

endmodule

learn/fn_sw/fn_sw_tb.v

module fn_sw_tb; reg a, b, sel; wire y;
    fn_sw fn_sw_tb(.a(a), .b(b), .sel(sel), .y(y));

    initial begin
        $dumpfile("learn/fn_sw/fn_sw.vcd");  // 指定VCD文件的名字为wave.vcd，仿真信息将记录到此文件
        $dumpvars(0, fn_sw_tb);  // 指定层次数为0，则tb_code 模块及其下面各层次的所有信号将被记录
        // #10000 $finish;
    end

    initial begin
        a     <= 0;b     <= 0;sel     <= 0;
        #10 a <= 0;b <= 0;sel <= 1;
        #10 a <= 0;b <= 1;sel <= 0;
        #10 a <= 0;b <= 1;sel <= 1;
        #10 a <= 1;b <= 0;sel <= 0;
        #10 a <= 1;b <= 0;sel <= 1;
        #10 a <= 1;b <= 1;sel <= 0;
        #10 a <= 1;b <= 1;sel <= 1;
        #10 $stop;
    end

endmodule

learn/fn_sw/fn_sw.vcd
$date
	Fri Nov 11 19:04:44 2022
$end
$version
	Icarus Verilog
$end
$timescale
	10ps
$end
$scope module fn_sw_tb $end
$scope module fn_sw_tb $end
$var wire 1 ! a $end
$var wire 1 " b $end
$var wire 1 # sel $end
$var reg 1 $ y $end
$upscope $end
$upscope $end
$enddefinitions $end
#0
$dumpvars
0$
0#
0"
0!
$end
#1000000000000
1#
#2000000000000
0#
1"
#3000000000000
1$
1#
#4000000000000
0$
0#
0"
1!
#5000000000000
1$
1#
#6000000000000
0#
1"
#7000000000000
0$
1#
