learn/s_counter/s_counter.v
module s_counter (clk,
                  res,
                  s_num);

    input clk,res;
    output[3:0] s_num;

    parameter freq_clk = 24; // 24Mhz

    reg[24:0] con_t; //秒脉冲分频计数器
    reg s_pulse; // 秒脉冲尖
    reg[3:0] s_num;

    always @(posedge clk or negedge res) begin
        if (~res)begin
            con_t   <= 0;
            s_pulse <= 0;
            s_num   <= 0;
        end
        else begin
            if (con_t == freq_clk*100-1)begin // 24MHz
                con_t <= 0;
            end
            else begin
                con_t <= con_t+1;
            end

            if (con_t == 0)begin
                s_pulse <= 1;
            end
            else begin
                s_pulse <= 0;
            end

            if (s_pulse==1)begin
                if (s_num == 9)begin
                    s_num <= 0;
                end
                else begin
                    s_num <= s_num+1;
                end
            end

        end

    end

endmodule //s_counter

learn/s_counter/s_counter_tb.v
`timescale 1ns/100ps
module s_counter_tb; reg clk, res; wire[3:0] s_num; s_counter s_counter_tb(.clk(clk), .res(res), .s_num(s_num));
    initial begin
        $dumpfile("learn/s_counter/s_counter.vcd");
        $dumpvars(0, s_counter_tb);
    end

    initial begin
        clk     <= 0;res     <= 0;
        #17 res <= 1;
        #1000000 $stop;
    end

    always  #5 clk <= ~clk;


endmodule //s_counter_tb

learn/s_counter/s_counter.vcd
$date
	Fri Nov 11 22:09:33 2022
$end
$version
	Icarus Verilog
$end
$timescale
	100ps
$end
$scope module s_counter_tb $end
$scope module s_counter_tb $end
$var wire 1 ! clk $end
$var wire 1 " res $end
$var reg 25 # con_t [24:0] $end
$var reg 4 $ s_num [3:0] $end
$var reg 1 % s_pulse $end
$upscope $end
$upscope $end
$enddefinitions $end
#0
$dumpvars
0%
b0 $
b0 #
0"
0!
$end
#50
1!
#100
0!
#150
1!
#170
1"
#200
0!
#250
1%
b1 #
1!
#300
0!
#350
b1 $
0%
b10 #
1!
#400
0!
#450
b11 #
1!
#500
0!
#550
b100 #
1!
#600
0!
#650
b101 #
1!
#700
0!
#750
b110 #
1!
#800
0!
#850
b111 #
1!
#900
0!
#950
b1000 #
1!
#1000
0!
#1050
b1001 #
1!
#1100
0!
#1150
b1010 #
1!
#1200
0!
#1250
b1011 #
1!
#1300
0!
#1350
b1100 #
1!
#1400
0!
#1450
b1101 #
1!
#1500
0!
#1550
b1110 #
1!
#1600
0!
#1650
b1111 #
1!
#1700
0!
#1750
b10000 #
1!
#1800
0!
#1850
b10001 #
1!
#1900
0!
#1950
b10010 #
1!
#2000
0!
#2050
b10011 #
1!
#2100
0!
#2150
b10100 #
1!
#2200
0!
#2250
b10101 #
1!
#2300
0!
#2350
b10110 #
1!
#2400
0!
#2450
b10111 #
1!
#2500
0!
#2550
b11000 #
1!
#2600
0!
#2650
b11001 #
1!
#2700
0!
#2750
b11010 #
1!
#2800
0!
#2850
b11011 #
1!
#2900
0!
#2950
b11100 #
1!
#3000
0!
#3050
b11101 #
1!
#3100
0!
#3150
b11110 #
1!
#3200
0!
#3250
b11111 #
1!
#3300
0!
#3350
b100000 #
1!
#3400
0!
#3450
b100001 #
1!
#3500
0!
#3550
b100010 #
1!
#3600
0!
#3650
b100011 #
1!
#3700
0!
#3750
b100100 #
1!
#3800
0!
#3850
b100101 #
1!
#3900
0!
#3950
b100110 #
1!
#4000
0!
#4050
b100111 #
1!
#4100
0!
#4150
b101000 #
1!
#4200
0!
#4250
b101001 #
1!
#4300
0!
#4350
b101010 #
1!
#4400
0!
#4450
b101011 #
1!
#4500
0!
#4550
b101100 #
1!
#4600
0!
#4650
b101101 #
1!
#4700
0!
#4750
b101110 #
1!
#4800
0!
#4850
b101111 #
1!
#4900
0!
#4950
b110000 #
1!
#5000
0!
#5050
b110001 #
1!
#5100
0!
#5150
b110010 #
1!
#5200
0!
#5250
b110011 #
1!
#5300
0!
#5350
b110100 #
1!
#5400
0!
#5450
b110101 #
1!
#5500
0!
#5550
b110110 #
1!
#5600
0!
#5650
b110111 #
1!
#5700
0!
#5750
b111000 #
1!
#5800
0!
#5850
b111001 #
1!
#5900
0!
#5950
b111010 #
1!
#6000
0!
#6050
b111011 #
1!
#6100
0!
#6150
b111100 #
1!
#6200
0!
#6250
b111101 #
1!
#6300
0!
#6350
b111110 #
1!
#6400
0!
#6450
b111111 #
1!
#6500
0!
#6550
b1000000 #
1!
#6600
0!
#6650
b1000001 #
1!
#6700
0!
#6750
b1000010 #
1!
#6800
0!
#6850
b1000011 #
1!
#6900
0!
#6950
b1000100 #
1!
#7000
0!
#7050
b1000101 #
1!
#7100
0!
#7150
b1000110 #
1!
#7200
0!
#7250
b1000111 #
1!
#7300
0!
#7350
b1001000 #
1!
#7400
0!
#7450
b1001001 #
1!
#7500
0!
#7550
b1001010 #
1!
#7600
0!
#7650
b1001011 #
1!
#7700
0!
#7750
b1001100 #
1!
#7800
0!
#7850
b1001101 #
1!
#7900
0!
#7950
b1001110 #
1!
#8000
0!
#8050
b1001111 #
1!
#8100
0!
#8150
b1010000 #
1!
#8200
0!
#8250
b1010001 #
1!
#8300
0!
#8350
b1010010 #
1!
#8400
0!
#8450
b1010011 #
1!
#8500
0!
#8550
b1010100 #
1!
#8600
0!
#8650
b1010101 #
1!
#8700
0!
#8750
b1010110 #
1!
#8800
0!
#8850
b1010111 #
1!
#8900
0!
#8950
b1011000 #
1!
#9000
0!
#9050
b1011001 #
1!
#9100
0!
#9150
b1011010 #
1!
#9200
0!
#9250
b1011011 #
1!
#9300
0!
#9350
b1011100 #
1!
#9400
0!
#9450
b1011101 #
1!
#9500
0!
#9550
b1011110 #
1!
#9600
0!
#9650
b1011111 #
1!
#9700
0!
#9750
b1100000 #
1!
#9800
0!
#9850
b1100001 #
1!
#9900
0!
#9950
b1100010 #
1!
#10000
0!
#10050
b1100011 #
1!
#10100
0!
#10150
b1100100 #
1!
#10200
0!
#10250
b1100101 #
1!
#10300
0!
#10350
b1100110 #
1!
#10400
0!
#10450
b1100111 #
1!
#10500
0!
#10550
b1101000 #
1!
#10600
0!
#10650
b1101001 #
1!
#10700
0!
#10750
b1101010 #
1!
#10800
0!
#10850
b1101011 #
1!
#10900
0!
#10950
b1101100 #
1!
#11000
0!
#11050
b1101101 #
1!
#11100
0!
#11150
b1101110 #
1!
#11200
0!
#11250
b1101111 #
1!
#11300
0!
#11350
b1110000 #
1!
#11400
0!
#11450
b1110001 #
1!
#11500
0!
#11550
b1110010 #
1!
#11600
0!
#11650
b1110011 #
1!
#11700
0!
#11750
b1110100 #
1!
#11800
0!
#11850
b1110101 #
1!
#11900
0!
#11950
b1110110 #
1!
#12000
0!
#12050
b1110111 #
1!
#12100
0!
#12150
b1111000 #
1!
#12200
0!
#12250
b1111001 #
1!
#12300
0!
#12350
b1111010 #
1!
#12400
0!
#12450
b1111011 #
1!
#12500
0!
#12550
b1111100 #
1!
#12600
0!
#12650
b1111101 #
1!
#12700
0!
#12750
b1111110 #
1!
#12800
0!
#12850
b1111111 #
1!
#12900
0!
#12950
b10000000 #
1!
#13000
0!
#13050
b10000001 #
1!
#13100
0!
#13150
b10000010 #
1!
#13200
0!
#13250
b10000011 #
1!
#13300
0!
#13350
b10000100 #
1!
#13400
0!
#13450
b10000101 #
1!
#13500
0!
#13550
b10000110 #
1!
#13600
0!
#13650
b10000111 #
1!
#13700
0!
#13750
b10001000 #
1!
#13800
0!
#13850
b10001001 #
1!
#13900
0!
#13950
b10001010 #
1!
#14000
0!
#14050
b10001011 #
1!
#14100
0!
#14150
b10001100 #
1!
#14200
0!
#14250
b10001101 #
1!
#14300
0!
#14350
b10001110 #
1!
#14400
0!
#14450
b10001111 #
1!
#14500
0!
#14550
b10010000 #
1!
#14600
0!
#14650
b10010001 #
1!
#14700
0!
#14750
b10010010 #
1!
#14800
0!
#14850
b10010011 #
1!
#14900
0!
#14950
b10010100 #
1!
#15000
0!
#15050
b10010101 #
1!
#15100
0!
#15150
b10010110 #
1!
#15200
0!
#15250
b10010111 #
1!
#15300
0!
#15350
b10011000 #
1!
#15400
0!
#15450
b10011001 #
1!
#15500
0!
#15550
b10011010 #
1!
#15600
0!
#15650
b10011011 #
1!
#15700
0!
#15750
b10011100 #
1!
#15800
0!
#15850
b10011101 #
1!
#15900
0!
#15950
b10011110 #
1!
#16000
0!
#16050
b10011111 #
1!
#16100
0!
#16150
b10100000 #
1!
#16200
0!
#16250
b10100001 #
1!
#16300
0!
#16350
b10100010 #
1!
#16400
0!
#16450
b10100011 #
1!
#16500
0!
#16550
b10100100 #
1!
#16600
0!
#16650
b10100101 #
1!
#16700
0!
#16750
b10100110 #
1!
#16800
0!
#16850
b10100111 #
1!
#16900
0!
#16950
b10101000 #
1!
#17000
0!
#17050
b10101001 #
1!
#17100
0!
#17150
b10101010 #
1!
#17200
0!
#17250
b10101011 #
1!
#17300
0!
#17350
b10101100 #
1!
#17400
0!
#17450
b10101101 #
1!
#17500
0!
#17550
b10101110 #
1!
#17600
0!
#17650
b10101111 #
1!
#17700
0!
#17750
b10110000 #
1!
#17800
0!
#17850
b10110001 #
1!
#17900
0!
#17950
b10110010 #
1!
#18000
0!
#18050
b10110011 #
1!
#18100
0!
#18150
b10110100 #
1!
#18200
0!
#18250
b10110101 #
1!
#18300
0!
#18350
b10110110 #
1!
#18400
0!
#18450
b10110111 #
1!
#18500
0!
#18550
b10111000 #
1!
#18600
0!
#18650
b10111001 #
1!
#18700
0!
#18750
b10111010 #
1!
#18800
0!
#18850
b10111011 #
1!
#18900
0!
#18950
b10111100 #
1!
#19000
0!
#19050
b10111101 #
1!
#19100
0!
#19150
b10111110 #
1!
#19200
0!
#19250
b10111111 #
1!
#19300
0!
#19350
b11000000 #
1!
#19400
0!
#19450
b11000001 #
1!
#19500
0!
#19550
b11000010 #
1!
#19600
0!
#19650
b11000011 #
1!
#19700
0!
#19750
b11000100 #
1!
#19800
0!
#19850
b11000101 #
1!
#19900
0!
#19950
b11000110 #
1!
#20000
0!
#20050
b11000111 #
1!
#20100
0!
#20150
b11001000 #
1!
#20200
0!
#20250
b11001001 #
1!
#20300
0!
#20350
b11001010 #
1!
#20400
0!
#20450
b11001011 #
1!
#20500
0!
#20550
b11001100 #
1!
#20600
0!
#20650
b11001101 #
1!
#20700
0!
#20750
b11001110 #
1!
#20800
0!
#20850
b11001111 #
1!
#20900
0!
#20950
b11010000 #
1!
#21000
0!
#21050
b11010001 #
1!
#21100
0!
#21150
b11010010 #
1!
#21200
0!
#21250
b11010011 #
1!
#21300
0!
#21350
b11010100 #
1!
#21400
0!
#21450
b11010101 #
1!
#21500
0!
#21550
b11010110 #
1!
#21600
0!
#21650
b11010111 #
1!
#21700
0!
#21750
b11011000 #
1!
#21800
0!
#21850
b11011001 #
1!
#21900
0!
#21950
b11011010 #
1!
#22000
0!
#22050
b11011011 #
1!
#22100
0!
#22150
b11011100 #
1!
#22200
0!
#22250
b11011101 #
1!
#22300
0!
#22350
b11011110 #
1!
#22400
0!
#22450
b11011111 #
1!
#22500
0!
#22550
b11100000 #
1!
#22600
0!
#22650
b11100001 #
1!
#22700
0!
#22750
b11100010 #
1!
#22800
0!
#22850
b11100011 #
1!
#22900
0!
#22950
b11100100 #
1!
#23000
0!
#23050
b11100101 #
1!
#23100
0!
#23150
b11100110 #
1!
#23200
0!
#23250
b11100111 #
1!
#23300
0!
#23350
b11101000 #
1!
#23400
0!
#23450
b11101001 #
1!
#23500
0!
#23550
b11101010 #
1!
#23600
0!
#23650
b11101011 #
1!
#23700
0!
#23750
b11101100 #
1!
#23800
0!
#23850
b11101101 #
1!
#23900
0!
#23950
b11101110 #
1!
#24000
0!
#24050
b11101111 #
1!
#24100
0!
#24150
b11110000 #
1!
#24200
0!
#24250
b11110001 #
1!
#24300
0!
#24350
b11110010 #
1!
#24400
0!
#24450
b11110011 #
1!
#24500
0!
#24550
b11110100 #
1!
#24600
0!
#24650
b11110101 #
1!
#24700
0!
#24750
b11110110 #
1!
#24800
0!
#24850
b11110111 #
1!
#24900
0!
#24950
b11111000 #
1!
#25000
0!
#25050
b11111001 #
1!
#25100
0!
#25150
b11111010 #
1!
#25200
0!
#25250
b11111011 #
1!
#25300
0!
#25350
b11111100 #
1!
#25400
0!
#25450
b11111101 #
1!
#25500
0!
#25550
b11111110 #
1!
#25600
0!
#25650
b11111111 #
1!
#25700
0!
#25750
b100000000 #
1!
#25800
0!
#25850
b100000001 #
1!
#25900
0!
#25950
b100000010 #
1!
#26000
0!
#26050
b100000011 #
1!
#26100
0!
#26150
b100000100 #
1!
#26200
0!
#26250
b100000101 #
1!
#26300
0!
#26350
b100000110 #
1!
#26400
0!
#26450
b100000111 #
1!
#26500
0!
#26550
b100001000 #
1!
#26600
0!
#26650
b100001001 #
1!
#26700
0!
#26750
b100001010 #
1!
#26800
0!
#26850
b100001011 #
1!
#26900
0!
#26950
b100001100 #
1!
#27000
0!
#27050
b100001101 #
1!
#27100
0!
#27150
b100001110 #
1!
#27200
0!
#27250
b100001111 #
1!
#27300
0!
#27350
b100010000 #
1!
#27400
0!
#27450
b100010001 #
1!
#27500
0!
#27550
b100010010 #
1!
#27600
0!
#27650
b100010011 #
1!
#27700
0!
#27750
b100010100 #
1!
#27800
0!
#27850
b100010101 #
1!
#27900
0!
#27950
b100010110 #
1!
#28000
0!
#28050
b100010111 #
1!
#28100
0!
#28150
b100011000 #
1!
#28200
0!
#28250
b100011001 #
1!
#28300
0!
#28350
b100011010 #
1!
#28400
0!
#28450
b100011011 #
1!
#28500
0!
#28550
b100011100 #
1!
#28600
0!
#28650
b100011101 #
1!
#28700
0!
#28750
b100011110 #
1!
#28800
0!
#28850
b100011111 #
1!
#28900
0!
#28950
b100100000 #
1!
#29000
0!
#29050
b100100001 #
1!
#29100
0!
#29150
b100100010 #
1!
#29200
0!
#29250
b100100011 #
1!
#29300
0!
#29350
b100100100 #
1!
#29400
0!
#29450
b100100101 #
1!
#29500
0!
#29550
b100100110 #
1!
#29600
0!
#29650
b100100111 #
1!
#29700
0!
#29750
b100101000 #
1!
#29800
0!
#29850
b100101001 #
1!
#29900
0!
#29950
b100101010 #
1!
#30000
0!
#30050
b100101011 #
1!
#30100
0!
#30150
b100101100 #
1!
#30200
0!
#30250
b100101101 #
1!
#30300
0!
#30350
b100101110 #
1!
#30400
0!
#30450
b100101111 #
1!
#30500
0!
#30550
b100110000 #
1!
#30600
0!
#30650
b100110001 #
1!
#30700
0!
#30750
b100110010 #
1!
#30800
0!
#30850
b100110011 #
1!
#30900
0!
#30950
b100110100 #
1!
#31000
0!
#31050
b100110101 #
1!
#31100
0!
#31150
b100110110 #
1!
#31200
0!
#31250
b100110111 #
1!
#31300
0!
#31350
b100111000 #
1!
#31400
0!
#31450
b100111001 #
1!
#31500
0!
#31550
b100111010 #
1!
#31600
0!
#31650
b100111011 #
1!
#31700
0!
#31750
b100111100 #
1!
#31800
0!
#31850
b100111101 #
1!
#31900
0!
#31950
b100111110 #
1!
#32000
0!
#32050
b100111111 #
1!
#32100
0!
#32150
b101000000 #
1!
#32200
0!
#32250
b101000001 #
1!
#32300
0!
#32350
b101000010 #
1!
#32400
0!
#32450
b101000011 #
1!
#32500
0!
#32550
b101000100 #
1!
#32600
0!
#32650
b101000101 #
1!
#32700
0!
#32750
b101000110 #
1!
#32800
0!
#32850
b101000111 #
1!
#32900
0!
#32950
b101001000 #
1!
#33000
0!
#33050
b101001001 #
1!
#33100
0!
#33150
b101001010 #
1!
#33200
0!
#33250
b101001011 #
1!
#33300
0!
#33350
b101001100 #
1!
#33400
0!
#33450
b101001101 #
1!
#33500
0!
#33550
b101001110 #
1!
#33600
0!
#33650
b101001111 #
1!
#33700
0!
#33750
b101010000 #
1!
#33800
0!
#33850
b101010001 #
1!
#33900
0!
#33950
b101010010 #
1!
#34000
0!
#34050
b101010011 #
1!
#34100
0!
#34150
b101010100 #
1!
#34200
0!
#34250
b101010101 #
1!
#34300
0!
#34350
b101010110 #
1!
#34400
0!
#34450
b101010111 #
1!
#34500
0!
#34550
b101011000 #
1!
#34600
0!
#34650
b101011001 #
1!
#34700
0!
#34750
b101011010 #
1!
#34800
0!
#34850
b101011011 #
1!
#34900
0!
#34950
b101011100 #
1!
#35000
0!
#35050
b101011101 #
1!
#35100
0!
#35150
b101011110 #
1!
#35200
0!
#35250
b101011111 #
1!
#35300
0!
#35350
b101100000 #
1!
#35400
0!
#35450
b101100001 #
1!
#35500
0!
#35550
b101100010 #
1!
#35600
0!
#35650
b101100011 #
1!
#35700
0!
#35750
b101100100 #
1!
#35800
0!
#35850
b101100101 #
1!
#35900
0!
#35950
b101100110 #
1!
#36000
0!
#36050
b101100111 #
1!
#36100
0!
#36150
b101101000 #
1!
#36200
0!
#36250
b101101001 #
1!
#36300
0!
#36350
b101101010 #
1!
#36400
0!
#36450
b101101011 #
1!
#36500
0!
#36550
b101101100 #
1!
#36600
0!
#36650
b101101101 #
1!
#36700
0!
#36750
b101101110 #
1!
#36800
0!
#36850
b101101111 #
1!
#36900
0!
#36950
b101110000 #
1!
#37000
0!
#37050
b101110001 #
1!
#37100
0!
#37150
b101110010 #
1!
#37200
0!
#37250
b101110011 #
1!
#37300
0!
#37350
b101110100 #
1!
#37400
0!
#37450
b101110101 #
1!
#37500
0!
#37550
b101110110 #
1!
#37600
0!
#37650
b101110111 #
1!
#37700
0!
#37750
b101111000 #
1!
#37800
0!
#37850
b101111001 #
1!
#37900
0!
#37950
b101111010 #
1!
#38000
0!
#38050
b101111011 #
1!
#38100
0!
#38150
b101111100 #
1!
#38200
0!
#38250
b101111101 #
1!
#38300
0!
#38350
b101111110 #
1!
#38400
0!
#38450
b101111111 #
1!
#38500
0!
#38550
b110000000 #
1!
#38600
0!
#38650
b110000001 #
1!
#38700
0!
#38750
b110000010 #
1!
#38800
0!
#38850
b110000011 #
1!
#38900
0!
#38950
b110000100 #
1!
#39000
0!
#39050
b110000101 #
1!
#39100
0!
#39150
b110000110 #
1!
#39200
0!
#39250
b110000111 #
1!
#39300
0!
#39350
b110001000 #
1!
#39400
0!
#39450
b110001001 #
1!
#39500
0!
#39550
b110001010 #
1!
#39600
0!
#39650
b110001011 #
1!
#39700
0!
#39750
b110001100 #
1!
#39800
0!
#39850
b110001101 #
1!
#39900
0!
#39950
b110001110 #
1!
#40000
0!
#40050
b110001111 #
1!
#40100
0!
#40150
b110010000 #
1!
#40200
0!
#40250
b110010001 #
1!
#40300
0!
#40350
b110010010 #
1!
#40400
0!
#40450
b110010011 #
1!
#40500
0!
#40550
b110010100 #
1!
#40600
0!
#40650
b110010101 #
1!
#40700
0!
#40750
b110010110 #
1!
#40800
0!
#40850
b110010111 #
1!
#40900
0!
#40950
b110011000 #
1!
#41000
0!
#41050
b110011001 #
1!
#41100
0!
#41150
b110011010 #
1!
#41200
0!
#41250
b110011011 #
1!
#41300
0!
#41350
b110011100 #
1!
#41400
0!
#41450
b110011101 #
1!
#41500
0!
#41550
b110011110 #
1!
#41600
0!
#41650
b110011111 #
1!
#41700
0!
#41750
b110100000 #
1!
#41800
0!
#41850
b110100001 #
1!
#41900
0!
#41950
b110100010 #
1!
#42000
0!
#42050
b110100011 #
1!
#42100
0!
#42150
b110100100 #
1!
#42200
0!
#42250
b110100101 #
1!
#42300
0!
#42350
b110100110 #
1!
#42400
0!
#42450
b110100111 #
1!
#42500
0!
#42550
b110101000 #
1!
#42600
0!
#42650
b110101001 #
1!
#42700
0!
#42750
b110101010 #
1!
#42800
0!
#42850
b110101011 #
1!
#42900
0!
#42950
b110101100 #
1!
#43000
0!
#43050
b110101101 #
1!
#43100
0!
#43150
b110101110 #
1!
#43200
0!
#43250
b110101111 #
1!
#43300
0!
#43350
b110110000 #
1!
#43400
0!
#43450
b110110001 #
1!
#43500
0!
#43550
b110110010 #
1!
#43600
0!
#43650
b110110011 #
1!
#43700
0!
#43750
b110110100 #
1!
#43800
0!
#43850
b110110101 #
1!
#43900
0!
#43950
b110110110 #
1!
#44000
0!
#44050
b110110111 #
1!
#44100
0!
#44150
b110111000 #
1!
#44200
0!
#44250
b110111001 #
1!
#44300
0!
#44350
b110111010 #
1!
#44400
0!
#44450
b110111011 #
1!
#44500
0!
#44550
b110111100 #
1!
#44600
0!
#44650
b110111101 #
1!
#44700
0!
#44750
b110111110 #
1!
#44800
0!
#44850
b110111111 #
1!
#44900
0!
#44950
b111000000 #
1!
#45000
0!
#45050
b111000001 #
1!
#45100
0!
#45150
b111000010 #
1!
#45200
0!
#45250
b111000011 #
1!
#45300
0!
#45350
b111000100 #
1!
#45400
0!
#45450
b111000101 #
1!
#45500
0!
#45550
b111000110 #
1!
#45600
0!
#45650
b111000111 #
1!
#45700
0!
#45750
b111001000 #
1!
#45800
0!
#45850
b111001001 #
1!
#45900
0!
#45950
b111001010 #
1!
#46000
0!
#46050
b111001011 #
1!
#46100
0!
#46150
b111001100 #
1!
#46200
0!
#46250
b111001101 #
1!
#46300
0!
#46350
b111001110 #
1!
#46400
0!
#46450
b111001111 #
1!
#46500
0!
#46550
b111010000 #
1!
#46600
0!
#46650
b111010001 #
1!
#46700
0!
#46750
b111010010 #
1!
#46800
0!
#46850
b111010011 #
1!
#46900
0!
#46950
b111010100 #
1!
#47000
0!
#47050
b111010101 #
1!
#47100
0!
#47150
b111010110 #
1!
#47200
0!
#47250
b111010111 #
1!
#47300
0!
#47350
b111011000 #
1!
#47400
0!
#47450
b111011001 #
1!
#47500
0!
#47550
b111011010 #
1!
#47600
0!
#47650
b111011011 #
1!
#47700
0!
#47750
b111011100 #
1!
#47800
0!
#47850
b111011101 #
1!
#47900
0!
#47950
b111011110 #
1!
#48000
0!
#48050
b111011111 #
1!
#48100
0!
#48150
b111100000 #
1!
#48200
0!
#48250
b111100001 #
1!
#48300
0!
#48350
b111100010 #
1!
#48400
0!
#48450
b111100011 #
1!
#48500
0!
#48550
b111100100 #
1!
#48600
0!
#48650
b111100101 #
1!
#48700
0!
#48750
b111100110 #
1!
#48800
0!
#48850
b111100111 #
1!
#48900
0!
#48950
b111101000 #
1!
#49000
0!
#49050
b111101001 #
1!
#49100
0!
#49150
b111101010 #
1!
#49200
0!
#49250
b111101011 #
1!
#49300
0!
#49350
b111101100 #
1!
#49400
0!
#49450
b111101101 #
1!
#49500
0!
#49550
b111101110 #
1!
#49600
0!
#49650
b111101111 #
1!
#49700
0!
#49750
b111110000 #
1!
#49800
0!
#49850
b111110001 #
1!
#49900
0!
#49950
b111110010 #
1!
#50000
0!
#50050
b111110011 #
1!
#50100
0!
#50150
b111110100 #
1!
#50200
0!
#50250
b111110101 #
1!
#50300
0!
#50350
b111110110 #
1!
#50400
0!
#50450
b111110111 #
1!
#50500
0!
#50550
b111111000 #
1!
#50600
0!
#50650
b111111001 #
1!
#50700
0!
#50750
b111111010 #
1!
#50800
0!
#50850
b111111011 #
1!
#50900
0!
#50950
b111111100 #
1!
#51000
0!
#51050
b111111101 #
1!
#51100
0!
#51150
b111111110 #
1!
#51200
0!
#51250
b111111111 #
1!
#51300
0!
#51350
b1000000000 #
1!
#51400
0!
#51450
b1000000001 #
1!
#51500
0!
#51550
b1000000010 #
1!
#51600
0!
#51650
b1000000011 #
1!
#51700
0!
#51750
b1000000100 #
1!
#51800
0!
#51850
b1000000101 #
1!
#51900
0!
#51950
b1000000110 #
1!
#52000
0!
#52050
b1000000111 #
1!
#52100
0!
#52150
b1000001000 #
1!
#52200
0!
#52250
b1000001001 #
1!
#52300
0!
#52350
b1000001010 #
1!
#52400
0!
#52450
b1000001011 #
1!
#52500
0!
#52550
b1000001100 #
1!
#52600
0!
#52650
b1000001101 #
1!
#52700
0!
#52750
b1000001110 #
1!
#52800
0!
#52850
b1000001111 #
1!
#52900
0!
#52950
b1000010000 #
1!
#53000
0!
#53050
b1000010001 #
1!
#53100
0!
#53150
b1000010010 #
1!
#53200
0!
#53250
b1000010011 #
1!
#53300
0!
#53350
b1000010100 #
1!
#53400
0!
#53450
b1000010101 #
1!
#53500
0!
#53550
b1000010110 #
1!
#53600
0!
#53650
b1000010111 #
1!
#53700
0!
#53750
b1000011000 #
1!
#53800
0!
#53850
b1000011001 #
1!
#53900
0!
#53950
b1000011010 #
1!
#54000
0!
#54050
b1000011011 #
1!
#54100
0!
#54150
b1000011100 #
1!
#54200
0!
#54250
b1000011101 #
1!
#54300
0!
#54350
b1000011110 #
1!
#54400
0!
#54450
b1000011111 #
1!
#54500
0!
#54550
b1000100000 #
1!
#54600
0!
#54650
b1000100001 #
1!
#54700
0!
#54750
b1000100010 #
1!
#54800
0!
#54850
b1000100011 #
1!
#54900
0!
#54950
b1000100100 #
1!
#55000
0!
#55050
b1000100101 #
1!
#55100
0!
#55150
b1000100110 #
1!
#55200
0!
#55250
b1000100111 #
1!
#55300
0!
#55350
b1000101000 #
1!
#55400
0!
#55450
b1000101001 #
1!
#55500
0!
#55550
b1000101010 #
1!
#55600
0!
#55650
b1000101011 #
1!
#55700
0!
#55750
b1000101100 #
1!
#55800
0!
#55850
b1000101101 #
1!
#55900
0!
#55950
b1000101110 #
1!
#56000
0!
#56050
b1000101111 #
1!
#56100
0!
#56150
b1000110000 #
1!
#56200
0!
#56250
b1000110001 #
1!
#56300
0!
#56350
b1000110010 #
1!
#56400
0!
#56450
b1000110011 #
1!
#56500
0!
#56550
b1000110100 #
1!
#56600
0!
#56650
b1000110101 #
1!
#56700
0!
#56750
b1000110110 #
1!
#56800
0!
#56850
b1000110111 #
1!
#56900
0!
#56950
b1000111000 #
1!
#57000
0!
#57050
b1000111001 #
1!
#57100
0!
#57150
b1000111010 #
1!
#57200
0!
#57250
b1000111011 #
1!
#57300
0!
#57350
b1000111100 #
1!
#57400
0!
#57450
b1000111101 #
1!
#57500
0!
#57550
b1000111110 #
1!
#57600
0!
#57650
b1000111111 #
1!
#57700
0!
#57750
b1001000000 #
1!
#57800
0!
#57850
b1001000001 #
1!
#57900
0!
#57950
b1001000010 #
1!
#58000
0!
#58050
b1001000011 #
1!
#58100
0!
#58150
b1001000100 #
1!
#58200
0!
#58250
b1001000101 #
1!
#58300
0!
#58350
b1001000110 #
1!
#58400
0!
#58450
b1001000111 #
1!
#58500
0!
#58550
b1001001000 #
1!
#58600
0!
#58650
b1001001001 #
1!
#58700
0!
#58750
b1001001010 #
1!
#58800
0!
#58850
b1001001011 #
1!
#58900
0!
#58950
b1001001100 #
1!
#59000
0!
#59050
b1001001101 #
1!
#59100
0!
#59150
b1001001110 #
1!
#59200
0!
#59250
b1001001111 #
1!
#59300
0!
#59350
b1001010000 #
1!
#59400
0!
#59450
b1001010001 #
1!
#59500
0!
#59550
b1001010010 #
1!
#59600
0!
#59650
b1001010011 #
1!
#59700
0!
#59750
b1001010100 #
1!
#59800
0!
#59850
b1001010101 #
1!
#59900
0!
#59950
b1001010110 #
1!
#60000
0!
#60050
b1001010111 #
1!
#60100
0!
#60150
b1001011000 #
1!
#60200
0!
#60250
b1001011001 #
1!
#60300
0!
#60350
b1001011010 #
1!
#60400
0!
#60450
b1001011011 #
1!
#60500
0!
#60550
b1001011100 #
1!
#60600
0!
#60650
b1001011101 #
1!
#60700
0!
#60750
b1001011110 #
1!
#60800
0!
#60850
b1001011111 #
1!
#60900
0!
#60950
b1001100000 #
1!
#61000
0!
#61050
b1001100001 #
1!
#61100
0!
#61150
b1001100010 #
1!
#61200
0!
#61250
b1001100011 #
1!
#61300
0!
#61350
b1001100100 #
1!
#61400
0!
#61450
b1001100101 #
1!
#61500
0!
#61550
b1001100110 #
1!
#61600
0!
#61650
b1001100111 #
1!
#61700
0!
#61750
b1001101000 #
1!
#61800
0!
#61850
b1001101001 #
1!
#61900
0!
#61950
b1001101010 #
1!
#62000
0!
#62050
b1001101011 #
1!
#62100
0!
#62150
b1001101100 #
1!
#62200
0!
#62250
b1001101101 #
1!
#62300
0!
#62350
b1001101110 #
1!
#62400
0!
#62450
b1001101111 #
1!
#62500
0!
#62550
b1001110000 #
1!
#62600
0!
#62650
b1001110001 #
1!
#62700
0!
#62750
b1001110010 #
1!
#62800
0!
#62850
b1001110011 #
1!
#62900
0!
#62950
b1001110100 #
1!
#63000
0!
#63050
b1001110101 #
1!
#63100
0!
#63150
b1001110110 #
1!
#63200
0!
#63250
b1001110111 #
1!
#63300
0!
#63350
b1001111000 #
1!
#63400
0!
#63450
b1001111001 #
1!
#63500
0!
#63550
b1001111010 #
1!
#63600
0!
#63650
b1001111011 #
1!
#63700
0!
#63750
b1001111100 #
1!
#63800
0!
#63850
b1001111101 #
1!
#63900
0!
#63950
b1001111110 #
1!
#64000
0!
#64050
b1001111111 #
1!
#64100
0!
#64150
b1010000000 #
1!
#64200
0!
#64250
b1010000001 #
1!
#64300
0!
#64350
b1010000010 #
1!
#64400
0!
#64450
b1010000011 #
1!
#64500
0!
#64550
b1010000100 #
1!
#64600
0!
#64650
b1010000101 #
1!
#64700
0!
#64750
b1010000110 #
1!
#64800
0!
#64850
b1010000111 #
1!
#64900
0!
#64950
b1010001000 #
1!
#65000
0!
#65050
b1010001001 #
1!
#65100
0!
#65150
b1010001010 #
1!
#65200
0!
#65250
b1010001011 #
1!
#65300
0!
#65350
b1010001100 #
1!
#65400
0!
#65450
b1010001101 #
1!
#65500
0!
#65550
b1010001110 #
1!
#65600
0!
#65650
b1010001111 #
1!
#65700
0!
#65750
b1010010000 #
1!
#65800
0!
#65850
b1010010001 #
1!
#65900
0!
#65950
b1010010010 #
1!
#66000
0!
#66050
b1010010011 #
1!
#66100
0!
#66150
b1010010100 #
1!
#66200
0!
#66250
b1010010101 #
1!
#66300
0!
#66350
b1010010110 #
1!
#66400
0!
#66450
b1010010111 #
1!
#66500
0!
#66550
b1010011000 #
1!
#66600
0!
#66650
b1010011001 #
1!
#66700
0!
#66750
b1010011010 #
1!
#66800
0!
#66850
b1010011011 #
1!
#66900
0!
#66950
b1010011100 #
1!
#67000
0!
